main.py
spawnm-0.2.1.dist-info/licenses/LICENSE
spawnm-0.2.1.dist-info/METADATA
spawnm-0.2.1.dist-info/WHEEL
spawnm-0.2.1.dist-info/entry_points.txt
spawnm-0.2.1.dist-info/top_level.txt
spawnm-0.2.1.dist-info/RECORD
