Metadata-Version: 2.4
Name: spawnm
Version: 0.2.1
Summary: Quickly spin up Hetzner instances
License-Expression: BSD-2-Clause
Requires-Python: >=3.9
License-File: LICENSE
Dynamic: license-file
